reportlib/__init__.py
reportlib/report.py
reportlib/utils/__init__.py
reportlib/utils/config_parser.py
reportlib/utils/stylesheet.py
reportlib/utils/pandas/__init__.py
reportlib/utils/pandas/monkey_patch.py
reportlib/utils/pandas/styler/__init__.py
reportlib/utils/pandas/styler/cell.py
reportlib/utils/pandas/styler/cell_range.py
reportlib/utils/pandas/styler/styler.py
reportlib/utils/templating/__init__.py
reportlib/utils/templating/template_loader.py
reportlib/utils/templating/templates/base/base.html
reportlib/utils/templating/templates/base/styles.css
reportlib/utils/templating/templates/base/table.html
reportlib-3.3.0.dist-info/METADATA
reportlib-3.3.0.dist-info/WHEEL
reportlib-3.3.0.dist-info/top_level.txt
reportlib-3.3.0.dist-info/RECORD
