Metadata-Version: 2.1
Name: reportlib
Version: 3.3.0
Summary: Generator HTML from pandas via Jinja2
Home-page: https://git.teko.vn/data/libs/reportlib
Author: nhat.nv
Author-email: nhat.nv@teko.vn
License: UNKNOWN
Platform: UNKNOWN
Classifier: Programming Language :: Python :: 3
Classifier: License :: OSI Approved :: MIT License
Classifier: Operating System :: OS Independent
Requires-Dist: css-html-js-minify (>=2.5)
Requires-Dist: htmlmin (>=0.1)
Requires-Dist: Jinja2 (>=2.10)
Requires-Dist: pandas (==0.24)
Requires-Dist: python-dateutil (>=2.8)
Requires-Dist: PyYAML (>=5.1)
Requires-Dist: premailer (>=3.5)
